pypdns/__init__.py
pypdns/api.py
python3_pdns-1.0.dist-info/METADATA
python3_pdns-1.0.dist-info/WHEEL
python3_pdns-1.0.dist-info/top_level.txt
python3_pdns-1.0.dist-info/RECORD
