Metadata-Version: 2.1
Name: python3-pdns
Version: 1.0
Summary: Binding python for passiveDNS Application
Home-page: https://github.com/PassivePDNS/pypdns
Author: Sebastien Larinier @sebdraven
License: UNKNOWN
Keywords: passiveDNS threat intel api
Platform: UNKNOWN
Requires-Python: >=3.8
Requires-Dist: requests
